pyrfid/__init__.py
pyrfid/pyrfid.py
pyrfid-1.2.dist-info/METADATA
pyrfid-1.2.dist-info/WHEEL
pyrfid-1.2.dist-info/top_level.txt
pyrfid-1.2.dist-info/RECORD
